gradian/__init__.py
gradian/compare_tree_counts.py
gradian/count_trees.py
gradian/sent_tree.py
gradian/super_glue_datasets_analyser.py
gradian/syntactic_dependency_counter.py
gradian/utils.py
GraDiAn-0.0.0.1.dist-info/LICENSE
GraDiAn-0.0.0.1.dist-info/METADATA
GraDiAn-0.0.0.1.dist-info/WHEEL
GraDiAn-0.0.0.1.dist-info/top_level.txt
GraDiAn-0.0.0.1.dist-info/RECORD
