Metadata-Version: 2.1
Name: GraDiAn
Version: 0.0.0.1
Summary: A grammatical distribution analyser for NLP datasets.
Home-page: https://github.com/adamjhawley/GraDiAn
Author: Adam Hawley
Author-email: ajh651@york.ac.uk
License: UNKNOWN
Platform: UNKNOWN
Classifier: Programming Language :: Python :: 3
Classifier: Operating System :: OS Independent
Classifier: Development Status :: 1 - Planning
Classifier: License :: OSI Approved :: GNU General Public License v3 (GPLv3)
Classifier: Natural Language :: English
Classifier: Topic :: Scientific/Engineering
Requires-Python: >=3.6
